calcs/__init__.py
calcs/annotate.py
calcs/call_cstag.py
calcs/convert.py
calcs/load.py
calcs/main.py
calcs/parse.py
calcs/tmp_main.py
calcs/trim.py
calcs-0.0.0.9999.dist-info/LICENSE
calcs-0.0.0.9999.dist-info/METADATA
calcs-0.0.0.9999.dist-info/WHEEL
calcs-0.0.0.9999.dist-info/entry_points.txt
calcs-0.0.0.9999.dist-info/top_level.txt
calcs-0.0.0.9999.dist-info/RECORD
