Metadata-Version: 2.1
Name: calcs
Version: 0.0.0.9999
Summary: call CS tag to SAM file
Home-page: https://github.com/akikuno/calcs
Author: Akihiro Kuno
Author-email: akuno@md.tsukuba.ac.jp
License: UNKNOWN
Platform: UNKNOWN
Classifier: Programming Language :: Python :: 3
Classifier: License :: OSI Approved :: MIT License
Classifier: Operating System :: OS Independent
Requires-Python: >=3.7
License-File: LICENSE
